bioneuralnet/__init__.py
bioneuralnet/clustering/__init__.py
bioneuralnet/clustering/correlated_louvain.py
bioneuralnet/clustering/correlated_pagerank.py
bioneuralnet/clustering/hybrid_louvain.py
bioneuralnet/datasets/__init__.py
bioneuralnet/datasets/dataset_loader.py
bioneuralnet/datasets/brca/clinical.csv
bioneuralnet/datasets/brca/meth.csv
bioneuralnet/datasets/brca/mirna.csv
bioneuralnet/datasets/brca/rna.csv
bioneuralnet/datasets/brca/target.csv
bioneuralnet/datasets/example/X1.csv
bioneuralnet/datasets/example/X2.csv
bioneuralnet/datasets/example/Y.csv
bioneuralnet/datasets/example/clinical.csv
bioneuralnet/datasets/kipan/clinical.csv
bioneuralnet/datasets/kipan/meth.csv
bioneuralnet/datasets/kipan/mirna.csv
bioneuralnet/datasets/kipan/rna.csv
bioneuralnet/datasets/kipan/target.csv
bioneuralnet/datasets/lgg/clinical.csv
bioneuralnet/datasets/lgg/meth.csv
bioneuralnet/datasets/lgg/mirna.csv
bioneuralnet/datasets/lgg/rna.csv
bioneuralnet/datasets/lgg/target.csv
bioneuralnet/datasets/monet/clinical.csv
bioneuralnet/datasets/monet/gene.csv
bioneuralnet/datasets/monet/mirna.csv
bioneuralnet/datasets/monet/phenotype.csv
bioneuralnet/datasets/monet/rppa.csv
bioneuralnet/datasets/paad/clinical.csv
bioneuralnet/datasets/paad/cnv.csv
bioneuralnet/datasets/paad/meth.csv
bioneuralnet/datasets/paad/rna.csv
bioneuralnet/datasets/paad/target.csv
bioneuralnet/downstream_task/__init__.py
bioneuralnet/downstream_task/dpmon.py
bioneuralnet/downstream_task/subject_representation.py
bioneuralnet/external_tools/SmCCNet.R
bioneuralnet/external_tools/__init__.py
bioneuralnet/external_tools/smccnet.py
bioneuralnet/metrics/__init__.py
bioneuralnet/metrics/correlation.py
bioneuralnet/metrics/plot.py
bioneuralnet/network_embedding/__init__.py
bioneuralnet/network_embedding/gnn_embedding.py
bioneuralnet/network_embedding/gnn_models.py
bioneuralnet/utils/__init__.py
bioneuralnet/utils/data.py
bioneuralnet/utils/graph.py
bioneuralnet/utils/graph_tools.py
bioneuralnet/utils/logger.py
bioneuralnet-1.2.2.dist-info/licenses/LICENSE
bioneuralnet-1.2.2.dist-info/METADATA
bioneuralnet-1.2.2.dist-info/WHEEL
bioneuralnet-1.2.2.dist-info/top_level.txt
bioneuralnet-1.2.2.dist-info/RECORD
