Metadata-Version: 2.4
Name: bioneuralnet
Version: 1.2.2
Summary: A Graph Neural Network based Multi-Omics Network Data Analysis Tool
Home-page: https://github.com/UCD-BDLab/BioNeuralNet
Author: Vicente Ramos
Author-email: vicente.ramos@ucdenver.edu
Project-URL: Bug Reports, https://github.com/UCD-BDLab/BioNeuralNet/issues
Project-URL: Source, https://github.com/UCD-BDLab/BioNeuralNet
Classifier: Programming Language :: Python :: 3
Classifier: License :: OSI Approved :: MIT License
Classifier: Operating System :: OS Independent
Classifier: Development Status :: 5 - Production/Stable
Requires-Python: >=3.10
License-File: LICENSE
Requires-Dist: pandas>=2.2.2
Requires-Dist: numpy>=1.26.4
Requires-Dist: scipy>=1.13.1
Requires-Dist: matplotlib>=3.10.3
Requires-Dist: scikit-learn>=1.6.1
Requires-Dist: statsmodels>=0.14.4
Requires-Dist: networkx>=3.4.2
Requires-Dist: python-louvain>=0.16
Requires-Dist: pydantic>=2.5
Requires-Dist: ray[train,tune]<2.53.0,>=2.46.0
Dynamic: license-file
